README.md
setup.py
ccalnoir/__init__.py
ccalnoir/ccal_style.py
ccalnoir/elemental.py
ccalnoir/information.py
ccalnoir/version.py
ccalnoir.egg-info/PKG-INFO
ccalnoir.egg-info/SOURCES.txt
ccalnoir.egg-info/dependency_links.txt
ccalnoir.egg-info/not-zip-safe
ccalnoir.egg-info/requires.txt
ccalnoir.egg-info/top_level.txt