Metadata-Version: 1.0
Name: ccalnoir
Version: 2.7
Summary: CCAL but with "No R".
Home-page: https://github.com/edjuaro/ccal-noir
Author: Edwin F. Juarez
Author-email: ejuarez@ucsd.edu
License: Modified BSD
Platform: UNKNOWN
